food_hygiene_mcp/__init__.py
food_hygiene_mcp/server.py
food_hygiene_mcp-0.1.1.dist-info/licenses/LICENSE
food_hygiene_mcp-0.1.1.dist-info/METADATA
food_hygiene_mcp-0.1.1.dist-info/WHEEL
food_hygiene_mcp-0.1.1.dist-info/entry_points.txt
food_hygiene_mcp-0.1.1.dist-info/top_level.txt
food_hygiene_mcp-0.1.1.dist-info/RECORD
