Metadata-Version: 2.4
Name: food-hygiene-mcp
Version: 0.1.1
Summary: MCP server for querying UK food hygiene ratings via the FSA API
License-Expression: MIT
Keywords: mcp,food-hygiene,fsa,uk,api,claude
Classifier: Development Status :: 4 - Beta
Classifier: Programming Language :: Python :: 3.14
Requires-Python: >=3.14
License-File: LICENSE
Requires-Dist: httpx>=0.28.1
Requires-Dist: mcp[cli]>=1.25.0
Dynamic: license-file
